Workbook

Sheet Campaign Data
A1: NOMUHUB | META CAMPAIGNS 2026 - INPUT SHEET
A2: 2026 figures only, taken month by month from Meta Ads Manager so every date is exact. Blue cells are typed in, white cells calculate. The Dashboard reads rows 5 to 21.
A4: Campaign Name | B4: Start Date | C4: First Month | D4: Last Month | E4: Months Live | F4: Status | G4: Objective | H4: Allocated Budget (SAR) | I4: Actual Spend (SAR) | J4: Results | K4: Impressions | L4: Reach | M4: Purchases | N4: Budget Remaining (SAR) | O4: Budget Used % | P4: Cost per Result (SAR) | Q4: CPM (SAR) | R4: Frequency
A5: 2026 Nomuhup Carousell | B5: 46201 | C5: Jun 2026 | D5: Aug 2026 | E5: 3 | F5: Inactive | G5: Messages | I5: 7463.84 | J5: 393 | K5: 144735 | L5: 46736 | M5: 6 | N5: =IF(H5="","",H5-I5) | O5: =IFERROR(I5/H5,"") | P5: =IFERROR(I5/J5,"") -> 18.991959 | Q5: =IFERROR(I5/K5*1000,"") -> 51.569005 | R5: =IFERROR(K5/L5,"") -> 3.0968632
A6: retarget sales | B6: 46054 | C6: Feb 2026 | D6: Aug 2026 | E6: 4 | F6: Active | G6: Purchases | I6: 2206.83 | J6: 4 | K6: 58487 | L6: 14024 | M6: 4 | N6: =IF(H6="","",H6-I6) | O6: =IFERROR(I6/H6,"") | P6: =IFERROR(I6/J6,"") -> 551.7075 | Q6: =IFERROR(I6/K6*1000,"") -> 37.731975 | R6: =IFERROR(K6/L6,"") -> 4.1704934
A7: ZNZ Build MSG - 2026 | B7: 46019 | C7: Jan 2026 | D7: Jan 2026 | E7: 1 | F7: Inactive | G7: Messages | I7: 2160.47 | J7: 163 | K7: 227256 | L7: 89491 | M7: 2 | N7: =IF(H7="","",H7-I7) | O7: =IFERROR(I7/H7,"") | P7: =IFERROR(I7/J7,"") -> 13.254417 | Q7: =IFERROR(I7/K7*1000,"") -> 9.5067677 | R7: =IFERROR(K7/L7,"") -> 2.5394285
A8: Discount Code | B8: 45706 | C8: Jan 2026 | D8: Feb 2026 | E8: 2 | F8: Inactive | G8: Messages | I8: 2133.61 | J8: 149 | K8: 84544 | L8: 16660 | M8: 1 | N8: =IF(H8="","",H8-I8) | O8: =IFERROR(I8/H8,"") | P8: =IFERROR(I8/J8,"") -> 14.31953 | Q8: =IFERROR(I8/K8*1000,"") -> 25.236681 | R8: =IFERROR(K8/L8,"") -> 5.0746699
A9: Vietnam explore sales | B9: 46049 | C9: Jan 2026 | D9: Feb 2026 | E9: 2 | F9: Inactive | G9: Purchases | I9: 1687.16 | J9: 1 | K9: 119526 | L9: 42722 | M9: 1 | N9: =IF(H9="","",H9-I9) | O9: =IFERROR(I9/H9,"") | P9: =IFERROR(I9/J9,"") -> 1687.16 | Q9: =IFERROR(I9/K9*1000,"") -> 14.115423 | R9: =IFERROR(K9/L9,"") -> 2.7977623
A10: Vietnam Explore MSG - 2026 | B10: 46037 | C10: Jan 2026 | D10: Jan 2026 | E10: 1 | F10: Inactive | G10: Messages | I10: 1082.58 | J10: 19 | K10: 44551 | L10: 21901 | M10: 0 | N10: =IF(H10="","",H10-I10) | O10: =IFERROR(I10/H10,"") | P10: =IFERROR(I10/J10,"") -> 56.977895 | Q10: =IFERROR(I10/K10*1000,"") -> 24.299791 | R10: =IFERROR(K10/L10,"") -> 2.0341994
A11: Thailan Wellness MSG - 2026 | B11: 46019 | C11: Jan 2026 | D11: Jan 2026 | E11: 1 | F11: Inactive | G11: Messages | I11: 982.25 | J11: 46 | K11: 21744 | L11: 12295 | M11: 0 | N11: =IF(H11="","",H11-I11) | O11: =IFERROR(I11/H11,"") | P11: =IFERROR(I11/J11,"") -> 21.353261 | Q11: =IFERROR(I11/K11*1000,"") -> 45.173381 | R11: =IFERROR(K11/L11,"") -> 1.7685238
A12: Bali Explore Msgs CPO | B12: 46243 | C12: Aug 2026 | D12: Aug 2026 | E12: 1 | F12: Inactive | G12: Messages | I12: 589.51 | J12: 25 | K12: 15487 | L12: 8432 | M12: 0 | N12: =IF(H12="","",H12-I12) | O12: =IFERROR(I12/H12,"") | P12: =IFERROR(I12/J12,"") -> 23.5804 | Q12: =IFERROR(I12/K12*1000,"") -> 38.064829 | R12: =IFERROR(K12/L12,"") -> 1.8366935
A13: ZNZ Explore Msgs CPO | B13: 46243 | C13: Aug 2026 | D13: Aug 2026 | E13: 1 | F13: Inactive | G13: Messages | I13: 463.59 | J13: 17 | K13: 11464 | L13: 6277 | M13: 0 | N13: =IF(H13="","",H13-I13) | O13: =IFERROR(I13/H13,"") | P13: =IFERROR(I13/J13,"") -> 27.27 | Q13: =IFERROR(I13/K13*1000,"") -> 40.438765 | R13: =IFERROR(K13/L13,"") -> 1.8263502
A14: ZNZ Medical - 2 | B14: 45995 | C14: Jan 2026 | D14: Jan 2026 | E14: 1 | F14: Inactive | G14: Messages | I14: 306.55 | J14: 43 | K14: 34974 | L14: 26283 | M14: 0 | N14: =IF(H14="","",H14-I14) | O14: =IFERROR(I14/H14,"") | P14: =IFERROR(I14/J14,"") -> 7.1290698 | Q14: =IFERROR(I14/K14*1000,"") -> 8.7650826 | R14: =IFERROR(K14/L14,"") -> 1.33067
A15: ZNZ Build10% | B15: 46256 | C15: Aug 2026 | D15: Aug 2026 | E15: 1 | F15: Active | G15: Messages | I15: 61.15 | J15: 12 | K15: 3865 | L15: 2894 | M15: 0 | N15: =IF(H15="","",H15-I15) | O15: =IFERROR(I15/H15,"") | P15: =IFERROR(I15/J15,"") -> 5.0958333 | Q15: =IFERROR(I15/K15*1000,"") -> 15.821475 | R15: =IFERROR(K15/L15,"") -> 1.3355218
A16: Bali Explore 10% | B16: 46256 | C16: Aug 2026 | D16: Aug 2026 | E16: 1 | F16: Active | G16: Messages | I16: 57.98 | J16: 7 | K16: 2143 | L16: 1700 | M16: 0 | N16: =IF(H16="","",H16-I16) | O16: =IFERROR(I16/H16,"") | P16: =IFERROR(I16/J16,"") -> 8.2828571 | Q16: =IFERROR(I16/K16*1000,"") -> 27.05553 | R16: =IFERROR(K16/L16,"") -> 1.2605882
A17: Vietnam Explore 10% | B17: 46256 | C17: Aug 2026 | D17: Aug 2026 | E17: 1 | F17: Active | G17: Messages | I17: 55.44 | J17: 3 | K17: 3041 | L17: 2472 | M17: 0 | N17: =IF(H17="","",H17-I17) | O17: =IFERROR(I17/H17,"") | P17: =IFERROR(I17/J17,"") -> 18.48 | Q17: =IFERROR(I17/K17*1000,"") -> 18.230845 | R17: =IFERROR(K17/L17,"") -> 1.230178
N18: =IF(H18="","",H18-I18) | O18: =IFERROR(I18/H18,"") | P18: =IFERROR(I18/J18,"") | Q18: =IFERROR(I18/K18*1000,"") | R18: =IFERROR(K18/L18,"")
N19: =IF(H19="","",H19-I19) | O19: =IFERROR(I19/H19,"") | P19: =IFERROR(I19/J19,"") | Q19: =IFERROR(I19/K19*1000,"") | R19: =IFERROR(K19/L19,"")
N20: =IF(H20="","",H20-I20) | O20: =IFERROR(I20/H20,"") | P20: =IFERROR(I20/J20,"") | Q20: =IFERROR(I20/K20*1000,"") | R20: =IFERROR(K20/L20,"")
N21: =IF(H21="","",H21-I21) | O21: =IFERROR(I21/H21,"") | P21: =IFERROR(I21/J21,"") | Q21: =IFERROR(I21/K21*1000,"") | R21: =IFERROR(K21/L21,"")
A22: TOTAL / AVERAGE | H22: =SUM(H5:H21) -> 0 | I22: =SUM(I5:I21) -> 19250.96 | J22: =SUM(J5:J21) -> 882 | K22: =SUM(K5:K21) -> 771817 | L22: =SUM(L5:L21) -> 291887 | M22: =SUM(M5:M21) -> 14 | N22: =IF(H22=0,"",H22-I22) | O22: =IFERROR(I22/H22,"") | P22: =IFERROR(I22/J22,"") -> 21.826485 | Q22: =IFERROR(I22/K22*1000,"") -> 24.942389 | R22: =IFERROR(K22/L22,"") -> 2.6442322

Sheet Dashboard
B3: META ADS | NOMUHUB 2026 | I3: ="Campaigns live in 2026: "&COUNTA('Campaign Data'!A5:A21)&" | Earlier years on Previous Trips tab" -> Campaigns live in 2026: 13 | Earlier years on Previous Trips tab
B6: PERFORMANCE | J6: SPEND BY OBJECTIVE
B8: ALLOCATED BUDGET | D8: ACTUAL SPEND | F8: BUDGET REMAINING | H8: BUDGET USED
B9: ='Campaign Data'!H22 -> 0 | D9: ='Campaign Data'!I22 -> 19250.96 | F9: ='Campaign Data'!N22 | H9: ='Campaign Data'!O22
B11: RESULTS | D11: COST PER RESULT | F11: IMPRESSIONS | H11: REACH
B12: ='Campaign Data'!J22 -> 882 | D12: ='Campaign Data'!P22 -> 21.826485 | F12: ='Campaign Data'!K22 -> 771817 | H12: ='Campaign Data'!L22 -> 291887
B14: FREQUENCY | D14: CPM | F14: PURCHASES | H14: CAMPAIGNS
B15: ='Campaign Data'!R22 -> 2.6442322 | D15: ='Campaign Data'!Q22 -> 24.942389 | F15: ='Campaign Data'!M22 -> 14 | H15: =COUNTA('Campaign Data'!A5:A21) -> 13
B19: BUDGET vs ACTUAL SPEND | H19: RESULTS BY CAMPAIGN
B35: PERFORMANCE BY CAMPAIGN OBJECTIVE
B36: Campaign Objective | D36: Campaigns | E36: Allocated | F36: Spend | G36: Impressions | H36: CPM | I36: Reach | J36: Purchases | K36: Results | L36: Cost/Result | M36: % of Spend
B37: Messages | D37: =COUNTIF('Campaign Data'!$G$5:$G$21,$B37) -> 11 | E37: =SUMIF('Campaign Data'!$G$5:$G$21,$B37,'Campaign Data'!$H$5:$H$21) -> 0 | F37: =SUMIF('Campaign Data'!$G$5:$G$21,$B37,'Campaign Data'!$I$5:$I$21) -> 15356.97 | G37: =SUMIF('Campaign Data'!$G$5:$G$21,$B37,'Campaign Data'!$K$5:$K$21) -> 593804 | H37: =IFERROR(F37/G37*1000,"") -> 25.862018 | I37: =SUMIF('Campaign Data'!$G$5:$G$21,$B37,'Campaign Data'!$L$5:$L$21) -> 235141 | J37: =SUMIF('Campaign Data'!$G$5:$G$21,$B37,'Campaign Data'!$M$5:$M$21) -> 9 | K37: =SUMIF('Campaign Data'!$G$5:$G$21,$B37,'Campaign Data'!$J$5:$J$21) -> 877 | L37: =IFERROR(F37/K37,"") -> 17.510798 | M37: =IFERROR(F37/'Campaign Data'!$I$22,"") -> 0.79772489
B38: Purchases | D38: =COUNTIF('Campaign Data'!$G$5:$G$21,$B38) -> 2 | E38: =SUMIF('Campaign Data'!$G$5:$G$21,$B38,'Campaign Data'!$H$5:$H$21) -> 0 | F38: =SUMIF('Campaign Data'!$G$5:$G$21,$B38,'Campaign Data'!$I$5:$I$21) -> 3893.99 | G38: =SUMIF('Campaign Data'!$G$5:$G$21,$B38,'Campaign Data'!$K$5:$K$21) -> 178013 | H38: =IFERROR(F38/G38*1000,"") -> 21.874751 | I38: =SUMIF('Campaign Data'!$G$5:$G$21,$B38,'Campaign Data'!$L$5:$L$21) -> 56746 | J38: =SUMIF('Campaign Data'!$G$5:$G$21,$B38,'Campaign Data'!$M$5:$M$21) -> 5 | K38: =SUMIF('Campaign Data'!$G$5:$G$21,$B38,'Campaign Data'!$J$5:$J$21) -> 5 | L38: =IFERROR(F38/K38,"") -> 778.798 | M38: =IFERROR(F38/'Campaign Data'!$I$22,"") -> 0.20227511
B39: Leads | D39: =COUNTIF('Campaign Data'!$G$5:$G$21,$B39) -> 0 | E39: =SUMIF('Campaign Data'!$G$5:$G$21,$B39,'Campaign Data'!$H$5:$H$21) -> 0 | F39: =SUMIF('Campaign Data'!$G$5:$G$21,$B39,'Campaign Data'!$I$5:$I$21) -> 0 | G39: =SUMIF('Campaign Data'!$G$5:$G$21,$B39,'Campaign Data'!$K$5:$K$21) -> 0 | H39: =IFERROR(F39/G39*1000,"") | I39: =SUMIF('Campaign Data'!$G$5:$G$21,$B39,'Campaign Data'!$L$5:$L$21) -> 0 | J39: =SUMIF('Campaign Data'!$G$5:$G$21,$B39,'Campaign Data'!$M$5:$M$21) -> 0 | K39: =SUMIF('Campaign Data'!$G$5:$G$21,$B39,'Campaign Data'!$J$5:$J$21) -> 0 | L39: =IFERROR(F39/K39,"") | M39: =IFERROR(F39/'Campaign Data'!$I$22,"") -> 0
B40: Link Clicks | D40: =COUNTIF('Campaign Data'!$G$5:$G$21,$B40) -> 0 | E40: =SUMIF('Campaign Data'!$G$5:$G$21,$B40,'Campaign Data'!$H$5:$H$21) -> 0 | F40: =SUMIF('Campaign Data'!$G$5:$G$21,$B40,'Campaign Data'!$I$5:$I$21) -> 0 | G40: =SUMIF('Campaign Data'!$G$5:$G$21,$B40,'Campaign Data'!$K$5:$K$21) -> 0 | H40: =IFERROR(F40/G40*1000,"") | I40: =SUMIF('Campaign Data'!$G$5:$G$21,$B40,'Campaign Data'!$L$5:$L$21) -> 0 | J40: =SUMIF('Campaign Data'!$G$5:$G$21,$B40,'Campaign Data'!$M$5:$M$21) -> 0 | K40: =SUMIF('Campaign Data'!$G$5:$G$21,$B40,'Campaign Data'!$J$5:$J$21) -> 0 | L40: =IFERROR(F40/K40,"") | M40: =IFERROR(F40/'Campaign Data'!$I$22,"") -> 0
B41: Reach | D41: =COUNTIF('Campaign Data'!$G$5:$G$21,$B41) -> 0 | E41: =SUMIF('Campaign Data'!$G$5:$G$21,$B41,'Campaign Data'!$H$5:$H$21) -> 0 | F41: =SUMIF('Campaign Data'!$G$5:$G$21,$B41,'Campaign Data'!$I$5:$I$21) -> 0 | G41: =SUMIF('Campaign Data'!$G$5:$G$21,$B41,'Campaign Data'!$K$5:$K$21) -> 0 | H41: =IFERROR(F41/G41*1000,"") | I41: =SUMIF('Campaign Data'!$G$5:$G$21,$B41,'Campaign Data'!$L$5:$L$21) -> 0 | J41: =SUMIF('Campaign Data'!$G$5:$G$21,$B41,'Campaign Data'!$M$5:$M$21) -> 0 | K41: =SUMIF('Campaign Data'!$G$5:$G$21,$B41,'Campaign Data'!$J$5:$J$21) -> 0 | L41: =IFERROR(F41/K41,"") | M41: =IFERROR(F41/'Campaign Data'!$I$22,"") -> 0
B42: Custom Conversion | D42: =COUNTIF('Campaign Data'!$G$5:$G$21,$B42) -> 0 | E42: =SUMIF('Campaign Data'!$G$5:$G$21,$B42,'Campaign Data'!$H$5:$H$21) -> 0 | F42: =SUMIF('Campaign Data'!$G$5:$G$21,$B42,'Campaign Data'!$I$5:$I$21) -> 0 | G42: =SUMIF('Campaign Data'!$G$5:$G$21,$B42,'Campaign Data'!$K$5:$K$21) -> 0 | H42: =IFERROR(F42/G42*1000,"") | I42: =SUMIF('Campaign Data'!$G$5:$G$21,$B42,'Campaign Data'!$L$5:$L$21) -> 0 | J42: =SUMIF('Campaign Data'!$G$5:$G$21,$B42,'Campaign Data'!$M$5:$M$21) -> 0 | K42: =SUMIF('Campaign Data'!$G$5:$G$21,$B42,'Campaign Data'!$J$5:$J$21) -> 0 | L42: =IFERROR(F42/K42,"") | M42: =IFERROR(F42/'Campaign Data'!$I$22,"") -> 0
B43: ALL OBJECTIVES | D43: =SUM(D37:D42) -> 13 | E43: =SUM(E37:E42) -> 0 | F43: =SUM(F37:F42) -> 19250.96 | G43: =SUM(G37:G42) -> 771817 | H43: =IFERROR(F43/G43*1000,"") -> 24.942389 | I43: =SUM(I37:I42) -> 291887 | J43: =SUM(J37:J42) -> 14 | K43: =SUM(K37:K42) -> 882 | L43: =IFERROR(F43/K43,"") -> 21.826485 | M43: =IFERROR(F43/'Campaign Data'!$I$22,"") -> 1
B46: All figures in SAR and cover 2026 only, month by month from Meta. Update the Campaign Data tab, this page refreshes on its own.

Sheet Previous Trips
B2: NOMUHUB | PREVIOUS TRIPS - FULL CAMPAIGN ARCHIVE BY YEAR
B5: One row per campaign per year, with the exact months it ran, taken from Meta's month by month delivery data across both NomuHub ad accounts. Reference only
B6: ROWS (CAMPAIGN x YEAR) | D6: TOTAL SPENT | F6: ROWS WITH SPEND | H6: TOTAL IMPRESSIONS | K6: TOTAL REACH | M6: TOTAL PURCHASES | O6: EXACT START DATES FOUND | Q6: USD to SAR RATE | T6: SPEND BY YEAR
B7: =COUNTA(B9:B156) -> 148 | D7: =SUM(L9:L156) -> 414246.19 | F7: =COUNTIF(L9:L156,">0") -> 103 | H7: =SUM(O9:O156) -> 69526460 | K7: =SUM(P9:P156) -> 24471044 | M7: =SUM(Q9:Q156) -> 66 | O7: =COUNT(S9:S156) -> 102 | Q7: 3.75 | T7: amber years = figures purged by Meta
B8: Campaign Name | C8: Year | D8: First Month | E8: Last Month | F8: Months Live | G8: Ad Account | H8: Status | I8: Objective | J8: Spend (orig) | K8: Cur | L8: Spend (SAR) | M8: Results | N8: Cost per Result (SAR) | O8: Impressions | P8: Reach | Q8: Purchases | R8: Date Source | S8: Campaign Start Date | T8: Year | U8: Spend (SAR) | V8: Campaigns
B9: Summer 2019 - New - Copy | C9: 2019 | D9: Purged by Meta | E9: Purged by Meta | G9: Nomuhub ad account | H9: Inactive | I9: No delivery | J9: 0 | K9: SAR | L9: =IF(K9="USD",J9*$Q$7,J9) -> 0 | N9: =IFERROR(L9/M9,"") | R9: Ran before Jul 2023, figures purged | S9: not in master file | T9: 2019 | U9: =SUMIF($C$9:$C$156,$T9,$L$9:$L$156) -> 0 | V9: =COUNTIF($C$9:$C$156,$T9) -> 4
B10: Morocco Summer 2019 campaign | C10: 2019 | D10: Purged by Meta | E10: Purged by Meta | G10: Nomuhub ad account | H10: Inactive | I10: No delivery | J10: 0 | K10: SAR | L10: =IF(K10="USD",J10*$Q$7,J10) -> 0 | N10: =IFERROR(L10/M10,"") | R10: Ran before Jul 2023, figures purged | S10: not in master file | T10: 2021 | U10: =SUMIF($C$9:$C$156,$T10,$L$9:$L$156) -> 0 | V10: =COUNTIF($C$9:$C$156,$T10) -> 6
B11: Zanzibar April 2019 | C11: 2019 | D11: Purged by Meta | E11: Purged by Meta | G11: Nomuhub ad account | H11: Inactive | I11: No delivery | J11: 0 | K11: SAR | L11: =IF(K11="USD",J11*$Q$7,J11) -> 0 | N11: =IFERROR(L11/M11,"") | R11: Ran before Jul 2023, figures purged | S11: not in master file | T11: 2022 | U11: =SUMIF($C$9:$C$156,$T11,$L$9:$L$156) -> 0 | V11: =COUNTIF($C$9:$C$156,$T11) -> 2
B12: Summer 2019 (first ad) | C12: 2019 | D12: Purged by Meta | E12: Purged by Meta | G12: Nomuhub ad account | H12: Inactive | I12: No delivery | J12: 0 | K12: SAR | L12: =IF(K12="USD",J12*$Q$7,J12) -> 0 | N12: =IFERROR(L12/M12,"") | R12: Ran before Jul 2023, figures purged | S12: not in master file | T12: 2023 | U12: =SUMIF($C$9:$C$156,$T12,$L$9:$L$156) -> 94094.42 | V12: =COUNTIF($C$9:$C$156,$T12) -> 18
B13: Retargeting_OCT_2021 | C13: 2021 | D13: Purged by Meta | E13: Purged by Meta | G13: Nomuhub ad account | H13: Archived | I13: No delivery | J13: 0 | K13: SAR | L13: =IF(K13="USD",J13*$Q$7,J13) -> 0 | N13: =IFERROR(L13/M13,"") | R13: Ran before Jul 2023, figures purged | S13: not in master file | T13: 2024 | U13: =SUMIF($C$9:$C$156,$T13,$L$9:$L$156) -> 191208.71 | V13: =COUNTIF($C$9:$C$156,$T13) -> 57
B14: Winter_GCCAudience25102021_conversions | C14: 2021 | D14: Purged by Meta | E14: Purged by Meta | G14: Nomuhub ad account | H14: Inactive | I14: No delivery | J14: 0 | K14: SAR | L14: =IF(K14="USD",J14*$Q$7,J14) -> 0 | N14: =IFERROR(L14/M14,"") | R14: Ran before Jul 2023, figures purged | S14: not in master file | T14: 2025 | U14: =SUMIF($C$9:$C$156,$T14,$L$9:$L$156) -> 128943.06 | V14: =COUNTIF($C$9:$C$156,$T14) -> 34
B15: GCCBroaderAudience_Septrip_2021 | C15: 2021 | D15: Purged by Meta | E15: Purged by Meta | G15: Nomuhub ad account | H15: Inactive | I15: No delivery | J15: 0 | K15: SAR | L15: =IF(K15="USD",J15*$Q$7,J15) -> 0 | N15: =IFERROR(L15/M15,"") | R15: Ran before Jul 2023, figures purged | S15: not in master file | T15: Never delivered | U15: =SUMIF($C$9:$C$156,$T15,$L$9:$L$156) -> 0 | V15: =COUNTIF($C$9:$C$156,$T15) -> 27
B16: PRO_GCCBroaderAudience18082021 | C16: 2021 | D16: Purged by Meta | E16: Purged by Meta | G16: Nomuhub ad account | H16: Inactive | I16: No delivery | J16: 0 | K16: SAR | L16: =IF(K16="USD",J16*$Q$7,J16) -> 0 | N16: =IFERROR(L16/M16,"") | R16: Ran before Jul 2023, figures purged | S16: not in master file
B17: Retargeting_sep_2021 | C17: 2021 | D17: Purged by Meta | E17: Purged by Meta | G17: Nomuhub ad account | H17: Inactive | I17: No delivery | J17: 0 | K17: SAR | L17: =IF(K17="USD",J17*$Q$7,J17) -> 0 | N17: =IFERROR(L17/M17,"") | R17: Ran before Jul 2023, figures purged | S17: not in master file
B18: RET_Websitevisitors,Videoviewers,Eanagers_SeptTrips 18082021 | C18: 2021 | D18: Purged by Meta | E18: Purged by Meta | G18: Nomuhub ad account | H18: Inactive | I18: No delivery | J18: 0 | K18: SAR | L18: =IF(K18="USD",J18*$Q$7,J18) -> 0 | N18: =IFERROR(L18/M18,"") | R18: Ran before Jul 2023, figures purged | S18: not in master file
B19: Summer_Campaign_2022_Traffic | C19: 2022 | D19: Purged by Meta | E19: Purged by Meta | G19: Nomuhub ad account | H19: Inactive | I19: No delivery | J19: 0 | K19: SAR | L19: =IF(K19="USD",J19*$Q$7,J19) -> 0 | N19: =IFERROR(L19/M19,"") | R19: Ran before Jul 2023, figures purged | S19: not in master file
B20: Retargeting_Reach_Winter2022 | C20: 2022 | D20: Purged by Meta | E20: Purged by Meta | G20: Nomuhub ad account | H20: Inactive | I20: Reach | J20: 0 | K20: SAR | L20: =IF(K20="USD",J20*$Q$7,J20) -> 0 | N20: =IFERROR(L20/M20,"") | R20: Ran before Jul 2023, figures purged | S20: not in master file
B21: August Sales Campaign 2023 | C21: 2023 | D21: Jul 2023 | E21: Oct 2023 | F21: 4 | G21: Nomuhub ad account | H21: Inactive | I21: Custom Conversion | J21: 42615.52 | K21: SAR | L21: =IF(K21="USD",J21*$Q$7,J21) -> 42615.52 | M21: 162411 | N21: =IFERROR(L21/M21,"") -> 0.26239306 | O21: 20231220 | P21: 5320895 | R21: Meta delivery data | S21: 45114
B22: Oct Nov Dec Leads Campaign 2023 | C22: 2023 | D22: Aug 2023 | E22: Nov 2023 | F22: 4 | G22: Nomuhub ad account | H22: Inactive | I22: Custom Conversion | J22: 20000 | K22: SAR | L22: =IF(K22="USD",J22*$Q$7,J22) -> 20000 | M22: 132874 | N22: =IFERROR(L22/M22,"") -> 0.15051854 | O22: 10731816 | P22: 2932405 | R22: Meta delivery data | S22: 45158
B23: Zanzibar_Leads_2023 | C23: 2023 | D23: Nov 2023 | E23: Dec 2023 | F23: 2 | G23: Nomuhub ad account | H23: Inactive | I23: Custom Conversion | J23: 9054.98 | K23: SAR | L23: =IF(K23="USD",J23*$Q$7,J23) -> 9054.98 | M23: 37115 | N23: =IFERROR(L23/M23,"") -> 0.2439709 | O23: 4609157 | P23: 1354502 | R23: Meta delivery data | S23: 45246
B24: Bali_Leads_2023 | C24: 2023 | D24: Nov 2023 | E24: Dec 2023 | F24: 2 | G24: Nomuhub ad account | H24: Inactive | I24: Custom Conversion | J24: 6419.79 | K24: SAR | L24: =IF(K24="USD",J24*$Q$7,J24) -> 6419.79 | M24: 37197 | N24: =IFERROR(L24/M24,"") -> 0.17258892 | O24: 3066398 | P24: 804440 | R24: Meta delivery data | S24: 45252
B25: Alula campaign 2023 | C25: 2023 | D25: Sep 2023 | E25: Oct 2023 | F25: 2 | G25: Nomuhub ad account | H25: Inactive | I25: Link Clicks | J25: 5625 | K25: SAR | L25: =IF(K25="USD",J25*$Q$7,J25) -> 5625 | M25: 58817 | N25: =IFERROR(L25/M25,"") -> 0.095635616 | O25: 1694913 | P25: 953620 | R25: Meta delivery data | S25: 45194
B26: Italy Blue Zone 2023 / Explore + Kenya | C26: 2023 | D26: Sep 2023 | E26: Oct 2023 | F26: 2 | G26: Nomuhub ad account | H26: Inactive | I26: Custom Conversion | J26: 2630.62 | K26: SAR | L26: =IF(K26="USD",J26*$Q$7,J26) -> 2630.62 | M26: 2599 | N26: =IFERROR(L26/M26,"") -> 1.0121662 | O26: 888041 | P26: 174599 | R26: Meta delivery data | S26: 45194
B27: SriLanka_Leads_2023 | C27: 2023 | D27: Nov 2023 | E27: Dec 2023 | F27: 2 | G27: Nomuhub ad account | H27: Inactive | I27: Custom Conversion | J27: 2199.17 | K27: SAR | L27: =IF(K27="USD",J27*$Q$7,J27) -> 2199.17 | M27: 11832 | N27: =IFERROR(L27/M27,"") -> 0.18586629 | O27: 1374077 | P27: 412394 | R27: Meta delivery data | S27: 45252
B28: ZNZ_Building_2023 | C28: 2023 | D28: Jul 2023 | E28: Aug 2023 | F28: 2 | G28: Nomuhub ad account | H28: Inactive | I28: Custom Conversion | J28: 1931.12 | K28: SAR | L28: =IF(K28="USD",J28*$Q$7,J28) -> 1931.12 | M28: 907 | N28: =IFERROR(L28/M28,"") -> 2.129129 | O28: 123605 | P28: 64110 | R28: Meta delivery data | S28: 45040
B29: Dooma_Awareness_2023 | C29: 2023 | D29: Sep 2023 | E29: Oct 2023 | F29: 2 | G29: Nomuhub ad account | H29: Inactive | I29: Reach | J29: 1500 | K29: SAR | L29: =IF(K29="USD",J29*$Q$7,J29) -> 1500 | M29: 555683 | N29: =IFERROR(L29/M29,"") -> 0.0026993808 | O29: 776137 | P29: 555683 | R29: Meta delivery data | S29: 45194
B30: Kenya_Sales_2023 | C30: 2023 | D30: Dec 2023 | E30: Dec 2023 | F30: 1 | G30: Nomuhub ad account | H30: Inactive | I30: Custom Conversion | J30: 1234.07 | K30: SAR | L30: =IF(K30="USD",J30*$Q$7,J30) -> 1234.07 | M30: 1284 | N30: =IFERROR(L30/M30,"") -> 0.96111371 | O30: 225410 | P30: 109148 | R30: Meta delivery data | S30: 45263
B31: Leads_AncientKingdoms_2023 | C31: 2023 | D31: Nov 2023 | E31: Nov 2023 | F31: 1 | G31: Nomuhub ad account | H31: Inactive | I31: Custom Conversion | J31: 590.89 | K31: SAR | L31: =IF(K31="USD",J31*$Q$7,J31) -> 590.89 | M31: 692 | N31: =IFERROR(L31/M31,"") -> 0.85388728 | O31: 73168 | P31: 47071 | R31: Meta delivery data | S31: 45245
B32: Bali Building_2023 | C32: 2023 | D32: Jul 2023 | E32: Jul 2023 | F32: 1 | G32: Nomuhub ad account | H32: Inactive | I32: Custom Conversion | J32: 293.26 | K32: SAR | L32: =IF(K32="USD",J32*$Q$7,J32) -> 293.26 | M32: 418 | N32: =IFERROR(L32/M32,"") -> 0.70157895 | O32: 76694 | P32: 50306 | R32: Meta delivery data | S32: 45058
B33: Zanzibar Teaching_2023 | C33: 2023 | D33: Purged by Meta | E33: Purged by Meta | G33: Nomuhub ad account | H33: Inactive | I33: No delivery | J33: 0 | K33: SAR | L33: =IF(K33="USD",J33*$Q$7,J33) -> 0 | N33: =IFERROR(L33/M33,"") | R33: Ran before Jul 2023, figures purged | S33: not in master file
B34: Kenya_Safari_2023 | C34: 2023 | D34: Purged by Meta | E34: Purged by Meta | G34: Nomuhub ad account | H34: Inactive | I34: No delivery | J34: 0 | K34: SAR | L34: =IF(K34="USD",J34*$Q$7,J34) -> 0 | N34: =IFERROR(L34/M34,"") | R34: Ran before Jul 2023, figures purged | S34: not in master file
B35: Explore_Trips_2023 | C35: 2023 | D35: Purged by Meta | E35: Purged by Meta | G35: Nomuhub ad account | H35: Inactive | I35: No delivery | J35: 0 | K35: SAR | L35: =IF(K35="USD",J35*$Q$7,J35) -> 0 | N35: =IFERROR(L35/M35,"") | R35: Ran before Jul 2023, figures purged | S35: not in master file
B36: Winter_2023 | C36: 2023 | D36: Purged by Meta | E36: Purged by Meta | G36: Nomuhub ad account | H36: Inactive | I36: No delivery | J36: 0 | K36: SAR | L36: =IF(K36="USD",J36*$Q$7,J36) -> 0 | N36: =IFERROR(L36/M36,"") | R36: Ran before Jul 2023, figures purged | S36: not in master file
B37: Welness Trip 2023 | C37: 2023 | D37: Purged by Meta | E37: Purged by Meta | G37: Nomuhub ad account | H37: Inactive | I37: No delivery | J37: 0 | K37: SAR | L37: =IF(K37="USD",J37*$Q$7,J37) -> 0 | N37: =IFERROR(L37/M37,"") | R37: Ran before Jul 2023, figures purged | S37: not in master file
B38: August 2023 Sales Campaign Campaign | C38: 2023 | D38: Purged by Meta | E38: Purged by Meta | G38: Nomuhub ad account | H38: Archived | I38: No delivery | J38: 0 | K38: SAR | L38: =IF(K38="USD",J38*$Q$7,J38) -> 0 | N38: =IFERROR(L38/M38,"") | R38: Ran before Jul 2023, figures purged | S38: not in master file
B39: Bali MSG Build june | C39: 2024 | D39: May 2024 | E39: Jul 2024 | F39: 3 | G39: Nomuhub ad account | H39: Inactive | I39: Messages | J39: 10785.96 | K39: SAR | L39: =IF(K39="USD",J39*$Q$7,J39) -> 10785.96 | M39: 836 | N39: =IFERROR(L39/M39,"") -> 12.901866 | O39: 316806 | P39: 141359 | R39: Meta delivery data | S39: 45442
B40: Bali Wellness Dec | C40: 2024 | D40: Oct 2024 | E40: Dec 2024 | F40: 3 | G40: Nomuhub ad account | H40: Inactive | I40: Messages | J40: 8049.83 | K40: SAR | L40: =IF(K40="USD",J40*$Q$7,J40) -> 8049.83 | M40: 463 | N40: =IFERROR(L40/M40,"") -> 17.386242 | O40: 145774 | P40: 80505 | R40: Meta delivery data | S40: 45589
B41: ZNZ Explore MSG | C41: 2024 | D41: Oct 2024 | E41: Nov 2024 | F41: 2 | G41: Nomuhub ad account | H41: Inactive | I41: Messages | J41: 7178.6 | K41: SAR | L41: =IF(K41="USD",J41*$Q$7,J41) -> 7178.6 | M41: 296 | N41: =IFERROR(L41/M41,"") -> 24.252027 | O41: 158608 | P41: 88287 | R41: Meta delivery data | S41: 45584
B42: Vietnam MSG | C42: 2024 | D42: Jul 2024 | E42: Sep 2024 | F42: 3 | G42: Nomuhub ad account | H42: Inactive | I42: Messages | J42: 6792.49 | K42: SAR | L42: =IF(K42="USD",J42*$Q$7,J42) -> 6792.49 | M42: 259 | N42: =IFERROR(L42/M42,"") -> 26.22583 | O42: 118823 | P42: 54057 | R42: Meta delivery data | S42: 45490
B43: Bali_Leads_2023 | C43: 2024 | D43: Jan 2024 | E43: Feb 2024 | F43: 2 | G43: Nomuhub ad account | H43: Inactive | I43: Custom Conversion | J43: 6696.47 | K43: SAR | L43: =IF(K43="USD",J43*$Q$7,J43) -> 6696.47 | M43: 77357 | N43: =IFERROR(L43/M43,"") -> 0.086565792 | O43: 4535858 | P43: 1315386 | R43: Meta delivery data | S43: 45252
B44: Bali MSG ًwellness July | C44: 2024 | D44: Jun 2024 | E44: Jul 2024 | F44: 2 | G44: Nomuhub ad account | H44: Inactive | I44: Messages | J44: 6535.46 | K44: SAR | L44: =IF(K44="USD",J44*$Q$7,J44) -> 6535.46 | M44: 476 | N44: =IFERROR(L44/M44,"") -> 13.729958 | O44: 137326 | P44: 71823 | R44: Meta delivery data | S44: 45447
B45: Salal MSG | C45: 2024 | D45: Jul 2024 | E45: Aug 2024 | F45: 2 | G45: Nomuhub ad account | H45: Inactive | I45: Messages | J45: 6211.49 | K45: SAR | L45: =IF(K45="USD",J45*$Q$7,J45) -> 6211.49 | M45: 491 | N45: =IFERROR(L45/M45,"") -> 12.650692 | O45: 118639 | P45: 59384 | R45: Meta delivery data | S45: 45488
B46: Aseer MSG | C46: 2024 | D46: Aug 2024 | E46: Sep 2024 | F46: 2 | G46: Nomuhub ad account | H46: Inactive | I46: Messages | J46: 6049.3 | K46: SAR | L46: =IF(K46="USD",J46*$Q$7,J46) -> 6049.3 | M46: 455 | N46: =IFERROR(L46/M46,"") -> 13.295165 | O46: 182413 | P46: 70334 | R46: Meta delivery data | S46: 45517
B47: Thailand Wellness LP 2 edit | C47: 2024 | D47: Sep 2024 | E47: Nov 2024 | F47: 3 | G47: Nomuhub ad account | H47: Inactive | I47: Leads | J47: 6005.41 | K47: SAR | L47: =IF(K47="USD",J47*$Q$7,J47) -> 6005.41 | M47: 384 | N47: =IFERROR(L47/M47,"") -> 15.639089 | O47: 213589 | P47: 101681 | R47: Meta delivery data | S47: 45563
B48: Retargeting | C48: 2024 | D48: May 2024 | E48: Oct 2024 | F48: 6 | G48: Nomuhub ad account | H48: Inactive | I48: Messages | J48: 5838.31 | K48: SAR | L48: =IF(K48="USD",J48*$Q$7,J48) -> 5838.31 | M48: 345 | N48: =IFERROR(L48/M48,"") -> 16.922638 | O48: 199555 | P48: 87615 | R48: Meta delivery data | S48: 45414
B49: ZNZ Teaching | C49: 2024 | D49: Nov 2024 | E49: Dec 2024 | F49: 2 | G49: Nomuhub ad account | H49: Inactive | I49: Messages | J49: 5641.26 | K49: SAR | L49: =IF(K49="USD",J49*$Q$7,J49) -> 5641.26 | M49: 339 | N49: =IFERROR(L49/M49,"") -> 16.640885 | O49: 172525 | P49: 76818 | R49: Meta delivery data | S49: 45599
B50: ZNZ teach Aug | C50: 2024 | D50: Jun 2024 | E50: Jul 2024 | F50: 2 | G50: Nomuhub ad account | H50: Inactive | I50: Messages | J50: 5531.34 | K50: SAR | L50: =IF(K50="USD",J50*$Q$7,J50) -> 5531.34 | M50: 511 | N50: =IFERROR(L50/M50,"") -> 10.82454 | O50: 175989 | P50: 75784 | R50: Meta delivery data | S50: 45454
... B68: Srilanka Build MSG | C68: 2024 | D68: Apr 2024 | E68: May 2024 | F68: 2 | G68: Nomuhub ad account | H68: Inactive | I68: Messages | J68: 3098.66 | K68: SAR | L68: =IF(K68="USD",J68*$Q$7,J68) -> 3098.66 | M68: 325 | N68: =IFERROR(L68/M68,"") -> 9.5343385 | O68: 157041 | P68: 88999 | R68: Meta delivery data | S68: 45403
B69: AW Campaign Traffic | C69: 2024 | D69: Apr 2024 | E69: Jun 2024 | F69: 3 | G69: Nomu Hub | H69: Inactive | I69: Profile Visits | J69: 780.71 | K69: USD | L69: =IF(K69="USD",J69*$Q$7,J69) -> 2927.6625 | M69: 7607 | N69: =IFERROR(L69/M69,"") -> 0.38486427 | O69: 641967 | P69: 255435 | R69: Meta delivery data | S69: not in master file
B70: Zanzibar_Leads_2023 | C70: 2024 | D70: Jan 2024 | E70: Feb 2024 | F70: 2 | G70: Nomuhub ad account | H70: Inactive | I70: Custom Conversion | J70: 2865.74 | K70: SAR | L70: =IF(K70="USD",J70*$Q$7,J70) -> 2865.74 | M70: 84636 | N70: =IFERROR(L70/M70,"") -> 0.033859587 | O70: 1722795 | P70: 492971 | R70: Meta delivery data | S70: 45246
B71: General Awareness Campaign 040302024 | C71: 2024 | D71: Mar 2024 | E71: Apr 2024 | F71: 2 | G71: Nomuhub ad account | H71: Inactive | I71: Reach | J71: 2832.76 | K71: SAR | L71: =IF(K71="USD",J71*$Q$7,J71) -> 2832.76 | M71: 3562742 | N71: =IFERROR(L71/M71,"") -> 0.00079510669 | O71: 5352696 | P71: 3562742 | R71: Meta delivery data | S71: 45355
B72: Corporate | C72: 2024 | D72: Jun 2024 | E72: Jun 2024 | F72: 1 | G72: Nomuhub ad account | H72: Inactive | I72: Messages | J72: 2740.32 | K72: SAR | L72: =IF(K72="USD",J72*$Q$7,J72) -> 2740.32 | M72: 47 | N72: =IFERROR(L72/M72,"") -> 58.304681 | O72: 33471 | P72: 14946 | R72: Meta delivery data | S72: 45448
B73: Vietnam Msg Explore | C73: 2024 | D73: Dec 2024 | E73: Dec 2024 | F73: 1 | G73: Nomuhub ad account | H73: Inactive | I73: Messages | J73: 2677.33 | K73: SAR | L73: =IF(K73="USD",J73*$Q$7,J73) -> 2677.33 | M73: 126 | N73: =IFERROR(L73/M73,"") -> 21.248651 | O73: 62653 | P73: 20025 | R73: Meta delivery data | S73: 45639
B74: Morrocco MSG | C74: 2024 | D74: Apr 2024 | E74: Apr 2024 | F74: 1 | G74: Nomuhub ad account | H74: Inactive | I74: Messages | J74: 2283.82 | K74: SAR | L74: =IF(K74="USD",J74*$Q$7,J74) -> 2283.82 | M74: 158 | N74: =IFERROR(L74/M74,"") -> 14.454557 | O74: 65971 | P74: 30468 | R74: Meta delivery data | S74: 45387
B75: Zinzibar Building MSG - Copy | C75: 2024 | D75: Apr 2024 | E75: May 2024 | F75: 2 | G75: Nomuhub ad account | H75: Inactive | I75: Messages | J75: 2121.63 | K75: SAR | L75: =IF(K75="USD",J75*$Q$7,J75) -> 2121.63 | M75: 286 | N75: =IFERROR(L75/M75,"") -> 7.4182867 | O75: 97947 | P75: 52287 | R75: Meta delivery data | S75: 45387
B76: Sardinia MSG | C76: 2024 | D76: Apr 2024 | E76: Apr 2024 | F76: 1 | G76: Nomuhub ad account | H76: Inactive | I76: Messages | J76: 2009.22 | K76: SAR | L76: =IF(K76="USD",J76*$Q$7,J76) -> 2009.22 | M76: 96 | N76: =IFERROR(L76/M76,"") -> 20.929375 | O76: 43446 | P76: 20574 | R76: Meta delivery data | S76: 45387
B77: Zinzibar Building MSG Build june | C77: 2024 | D77: May 2024 | E77: May 2024 | F77: 1 | G77: Nomuhub ad account | H77: Inactive | I77: Messages | J77: 1823.72 | K77: SAR | L77: =IF(K77="USD",J77*$Q$7,J77) -> 1823.72 | M77: 227 | N77: =IFERROR(L77/M77,"") -> 8.0340088 | O77: 69812 | P77: 33538 | R77: Meta delivery data | S77: 45435
B78: Italy_Sales_220324 | C78: 2024 | D78: Mar 2024 | E78: Apr 2024 | F78: 2 | G78: Nomuhub ad account | H78: Inactive | I78: Custom Conversion | J78: 1728.6 | K78: SAR | L78: =IF(K78="USD",J78*$Q$7,J78) -> 1728.6 | M78: 27179 | N78: =IFERROR(L78/M78,"") -> 0.063600574 | O78: 494886 | P78: 203997 | R78: Meta delivery data | S78: 45373
B79: Thailand wellness sep MSG | C79: 2024 | D79: Sep 2024 | E79: Oct 2024 | F79: 2 | G79: Nomuhub ad account | H79: Inactive | I79: Messages | J79: 1693.64 | K79: SAR | L79: =IF(K79="USD",J79*$Q$7,J79) -> 1693.64 | M79: 73 | N79: =IFERROR(L79/M79,"") -> 23.200548 | O79: 26014 | P79: 15715 | R79: Meta delivery data | S79: 45557
B80: Kenya_Sales_2023 | C80: 2024 | D80: Jan 2024 | E80: Feb 2024 | F80: 2 | G80: Nomuhub ad account | H80: Inactive | I80: Custom Conversion | J80: 1688.07 | K80: SAR | L80: =IF(K80="USD",J80*$Q$7,J80) -> 1688.07 | M80: 2124 | N80: =IFERROR(L80/M80,"") -> 0.79475989 | O80: 290458 | P80: 159785 | R80: Meta delivery data | S80: 45263
B81: SriLanka_Leads_2023 | C81: 2024 | D81: Jan 2024 | E81: Jan 2024 | F81: 1 | G81: Nomuhub ad account | H81: Inactive | I81: Custom Conversion | J81: 1550.83 | K81: SAR | L81: =IF(K81="USD",J81*$Q$7,J81) -> 1550.83 | M81: 38262 | N81: =IFERROR(L81/M81,"") -> 0.040531859 | O81: 1320879 | P81: 425197 | R81: Meta delivery data | S81: 45252
... B89: Nepal Building Msgs | C89: 2024 | D89: Apr 2024 | E89: Apr 2024 | F89: 1 | G89: Nomuhub ad account | H89: Inactive | I89: Messages | J89: 405.51 | K89: SAR | L89: =IF(K89="USD",J89*$Q$7,J89) -> 405.51 | M89: 36 | N89: =IFERROR(L89/M89,"") -> 11.264167 | O89: 12898 | P89: 8272 | R89: Meta delivery data | S89: 45395
B90: Bali Explore July Contact | C90: 2024 | D90: Jul 2024 | E90: Jul 2024 | F90: 1 | G90: Nomuhub ad account | H90: Inactive | I90: No delivery | J90: 351.63 | K90: SAR | L90: =IF(K90="USD",J90*$Q$7,J90) -> 351.63 | N90: =IFERROR(L90/M90,"") | O90: 12734 | P90: 6363 | R90: Meta delivery data | S90: 45474
B91: Morrocco LP | C91: 2024 | D91: Sep 2024 | E91: Sep 2024 | F91: 1 | G91: Nomuhub ad account | H91: Inactive | I91: Leads | J91: 323.67 | K91: SAR | L91: =IF(K91="USD",J91*$Q$7,J91) -> 323.67 | M91: 34 | N91: =IFERROR(L91/M91,"") -> 9.5197059 | O91: 11560 | P91: 9749 | R91: Meta delivery data | S91: 45557
B92: AlUla MSG | C92: 2024 | D92: Sep 2024 | E92: Sep 2024 | F92: 1 | G92: Nomuhub ad account | H92: Inactive | I92: Messages | J92: 167.69 | K92: SAR | L92: =IF(K92="USD",J92*$Q$7,J92) -> 167.69 | M92: 20 | N92: =IFERROR(L92/M92,"") -> 8.3845 | O92: 2974 | P92: 2391 | R92: Meta delivery data | S92: 45546
B93: General_Awareness_Campaign_2024 | C93: 2024 | D93: Feb 2024 | E93: Feb 2024 | F93: 1 | G93: Nomuhub ad account | H93: Inactive | I93: Reach | J93: 78.41 | K93: SAR | L93: =IF(K93="USD",J93*$Q$7,J93) -> 78.41 | M93: 82594 | N93: =IFERROR(L93/M93,"") -> 0.00094934257 | O93: 84140 | P93: 82594 | R93: Meta delivery data | S93: 45339
B94: Leads Zinzipar Explore | C94: 2024 | D94: Apr 2024 | E94: Apr 2024 | F94: 1 | G94: Nomuhub ad account | H94: Inactive | I94: No delivery | J94: 49.25 | K94: SAR | L94: =IF(K94="USD",J94*$Q$7,J94) -> 49.25 | N94: =IFERROR(L94/M94,"") | O94: 1896 | P94: 1503 | R94: Meta delivery data | S94: 45410
B95: Engagement_Whatsapp_Campaign_2024 | C95: 2024 | D95: Feb 2024 | E95: Feb 2024 | F95: 1 | G95: Nomuhub ad account | H95: Inactive | I95: Messages | J95: 40.76 | K95: SAR | L95: =IF(K95="USD",J95*$Q$7,J95) -> 40.76 | M95: 7 | N95: =IFERROR(L95/M95,"") -> 5.8228571 | O95: 2669 | P95: 1907 | R95: Meta delivery data | S95: 45339
B96: Discount Code | C96: 2025 | D96: Feb 2025 | E96: Dec 2025 | F96: 11 | G96: Nomuhub ad account | H96: Inactive | I96: Messages | J96: 28595.45 | K96: SAR | L96: =IF(K96="USD",J96*$Q$7,J96) -> 28595.45 | M96: 2114 | N96: =IFERROR(L96/M96,"") -> 13.526703 | O96: 782133 | P96: 255086 | Q96: 22 | R96: Meta delivery data | S96: 45706
B97: TH Wellness | C97: 2025 | D97: Jan 2025 | E97: Jun 2025 | F97: 4 | G97: Nomuhub ad account | H97: Inactive | I97: Messages | J97: 9984.43 | K97: SAR | L97: =IF(K97="USD",J97*$Q$7,J97) -> 9984.43 | M97: 552 | N97: =IFERROR(L97/M97,"") -> 18.087736 | O97: 168975 | P97: 73500 | Q97: 5 | R97: Meta delivery data | S97: 45758
B98: ZNZ Building | C98: 2025 | D98: Feb 2025 | E98: Nov 2025 | F98: 4 | G98: Nomuhub ad account | H98: Inactive | I98: Messages | J98: 9196.42 | K98: SAR | L98: =IF(K98="USD",J98*$Q$7,J98) -> 9196.42 | M98: 497 | N98: =IFERROR(L98/M98,"") -> 18.503863 | O98: 164990 | P98: 74113 | Q98: 2 | R98: Meta delivery data | S98: 45708
B99: Korea Msg | C99: 2025 | D99: Feb 2025 | E99: Oct 2025 | F99: 6 | G99: Nomuhub ad account | H99: Inactive | I99: Messages | J99: 7403.86 | K99: SAR | L99: =IF(K99="USD",J99*$Q$7,J99) -> 7403.86 | M99: 376 | N99: =IFERROR(L99/M99,"") -> 19.691117 | O99: 219022 | P99: 98574 | Q99: 3 | R99: Meta delivery data | S99: 45889
B100: Philippines Building | C100: 2025 | D100: Jul 2025 | E100: Sep 2025 | F100: 3 | G100: Nomuhub ad account | H100: Inactive | I100: Messages | J100: 5285.98 | K100: SAR | L100: =IF(K100="USD",J100*$Q$7,J100) -> 5285.98 | M100: 222 | N100: =IFERROR(L100/M100,"") -> 23.810721 | O100: 112705 | P100: 45463 | Q100: 4 | R100: Meta delivery data | S100: 45866
B101: Bali Wellness | C101: 2025 | D101: Feb 2025 | E101: Apr 2025 | F101: 3 | G101: Nomuhub ad account | H101: Inactive | I101: Messages | J101: 4580.01 | K101: SAR | L101: =IF(K101="USD",J101*$Q$7,J101) -> 4580.01 | M101: 229 | N101: =IFERROR(L101/M101,"") -> 20.000044 | O101: 61283 | P101: 29150 | R101: Meta delivery data | S101: 45707
B102: Insta Visit | C102: 2025 | D102: Aug 2025 | E102: Nov 2025 | F102: 4 | G102: Nomuhub ad account | H102: Inactive | I102: Profile Visits | J102: 4342.55 | K102: SAR | L102: =IF(K102="USD",J102*$Q$7,J102) -> 4342.55 | M102: 9092 | N102: =IFERROR(L102/M102,"") -> 0.47762319 | O102: 477757 | P102: 246578 | Q102: 1 | R102: Meta delivery data | S102: 45873
B103: Bali Wellness december | C103: 2025 | D103: Nov 2025 | E103: Dec 2025 | F103: 2 | G103: Nomuhub ad account | H103: Inactive | I103: Messages | J103: 4229.81 | K103: SAR | L103: =IF(K103="USD",J103*$Q$7,J103) -> 4229.81 | M103: 286 | N103: =IFERROR(L103/M103,"") -> 14.789545 | O103: 60058 | P103: 30504 | Q103: 2 | R103: Meta delivery data | S103: 45971
B104: Bali Explore | C104: 2025 | D104: Jun 2025 | E104: Jul 2025 | F104: 2 | G104: Nomuhub ad account | H104: Inactive | I104: Messages | J104: 4211.23 | K104: SAR | L104: =IF(K104="USD",J104*$Q$7,J104) -> 4211.23 | M104: 262 | N104: =IFERROR(L104/M104,"") -> 16.073397 | O104: 90850 | P104: 48454 | Q104: 1 | R104: Meta delivery data | S104: 45820
B105: South Africa Campaign | C105: 2025 | D105: Feb 2025 | E105: Jul 2025 | F105: 5 | G105: Nomuhub ad account | H105: Inactive | I105: Messages | J105: 4194.12 | K105: SAR | L105: =IF(K105="USD",J105*$Q$7,J105) -> 4194.12 | M105: 79 | N105: =IFERROR(L105/M105,"") -> 53.090127 | O105: 98968 | P105: 44306 | Q105: 2 | R105: Meta delivery data | S105: 45711
B106: Thailan Wellness MSG | C106: 2025 | D106: Sep 2025 | E106: Oct 2025 | F106: 2 | G106: Nomuhub ad account | H106: Inactive | I106: Messages | J106: 4135.44 | K106: SAR | L106: =IF(K106="USD",J106*$Q$7,J106) -> 4135.44 | M106: 189 | N106: =IFERROR(L106/M106,"") -> 21.880635 | O106: 82288 | P106: 39006 | Q106: 3 | R106: Meta delivery data | S106: 45916
B107: BA Build | C107: 2025 | D107: Jun 2025 | E107: Jul 2025 | F107: 2 | G107: Nomuhub ad account | H107: Inactive | I107: Messages | J107: 4078.28 | K107: SAR | L107: =IF(K107="USD",J107*$Q$7,J107) -> 4078.28 | M107: 141 | N107: =IFERROR(L107/M107,"") -> 28.923972 | O107: 127919 | P107: 72705 | Q107: 1 | R107: Meta delivery data | S107: 45812
B108: ZNZ Medical - 2 | C108: 2025 | D108: Dec 2025 | E108: Dec 2025 | F108: 1 | G108: Nomuhub ad account | H108: Inactive | I108: Messages | J108: 4026.36 | K108: SAR | L108: =IF(K108="USD",J108*$Q$7,J108) -> 4026.36 | M108: 673 | N108: =IFERROR(L108/M108,"") -> 5.9827043 | O108: 397204 | P108: 109220 | Q108: 2 | R108: Meta delivery data | S108: 45995
B109: JP | C109: 2025 | D109: Apr 2025 | E109: Apr 2025 | F109: 1 | G109: Nomuhub ad account | H109: Inactive | I109: Messages | J109: 3796.03 | K109: SAR | L109: =IF(K109="USD",J109*$Q$7,J109) -> 3796.03 | M109: 250 | N109: =IFERROR(L109/M109,"") -> 15.18412 | O109: 143461 | P109: 64134 | Q109: 2 | R109: Meta delivery data | S109: 45750
B110: ZNZ Explore - Copy | C110: 2025 | D110: Feb 2025 | E110: May 2025 | F110: 4 | G110: Nomuhub ad account | H110: Inactive | I110: Messages | J110: 3667.06 | K110: SAR | L110: =IF(K110="USD",J110*$Q$7,J110) -> 3667.06 | M110: 184 | N110: =IFERROR(L110/M110,"") -> 19.929674 | O110: 51305 | P110: 28790 | Q110: 2 | R110: Meta delivery data | S110: 45708
B111: Bali wellness | C111: 2025 | D111: Aug 2025 | E111: Oct 2025 | F111: 2 | G111: Nomuhub ad account | H111: Inactive | I111: Messages | J111: 2738.17 | K111: SAR | L111: =IF(K111="USD",J111*$Q$7,J111) -> 2738.17 | M111: 172 | N111: =IFERROR(L111/M111,"") -> 15.919593 | O111: 38051 | P111: 18868 | Q111: 1 | R111: Meta delivery data | S111: 45877
B112: Vietnam Msg Explore | C112: 2025 | D112: Jan 2025 | E112: Jan 2025 | F112: 1 | G112: Nomuhub ad account | H112: Inactive | I112: Messages | J112: 2624.01 | K112: SAR | L112: =IF(K112="USD",J112*$Q$7,J112) -> 2624.01 | M112: 81 | N112: =IFERROR(L112/M112,"") -> 32.395185 | O112: 70865 | P112: 27343 | R112: Meta delivery data | S112: 45639
B113: ZNZ Medical | C113: 2025 | D113: Jan 2025 | E113: Jun 2025 | F113: 3 | G113: Nomuhub ad account | H113: Inactive | I113: Messages | J113: 2516.52 | K113: SAR | L113: =IF(K113="USD",J113*$Q$7,J113) -> 2516.52 | M113: 467 | N113: =IFERROR(L113/M113,"") -> 5.3886938 | O113: 170950 | P113: 80490 | Q113: 1 | R113: Meta delivery data | S113: 45805
B114: Morrocco Msg | C114: 2025 | D114: Feb 2025 | E114: Apr 2025 | F114: 3 | G114: Nomuhub ad account | H114: Inactive | I114: Messages | J114: 2401.82 | K114: SAR | L114: =IF(K114="USD",J114*$Q$7,J114) -> 2401.82 | M114: 63 | N114: =IFERROR(L114/M114,"") -> 38.124127 | O114: 40537 | P114: 19967 | Q114: 1 | R114: Meta delivery data | S114: 45714
B115: BA Well | C115: 2025 | D115: May 2025 | E115: Jul 2025 | F115: 3 | G115: Nomuhub ad account | H115: Inactive | I115: Messages | J115: 2378.9 | K115: SAR | L115: =IF(K115="USD",J115*$Q$7,J115) -> 2378.9 | M115: 120 | N115: =IFERROR(L115/M115,"") -> 19.824167 | O115: 42209 | P115: 24731 | Q115: 1 | R115: Meta delivery data | S115: 45807
B116: ZNZ Buildingg | C116: 2025 | D116: Jul 2025 | E116: Aug 2025 | F116: 2 | G116: Nomuhub ad account | H116: Inactive | I116: Messages | J116: 2218.79 | K116: SAR | L116: =IF(K116="USD",J116*$Q$7,J116) -> 2218.79 | M116: 105 | N116: =IFERROR(L116/M116,"") -> 21.131333 | O116: 55291 | P116: 22180 | Q116: 2 | R116: Meta delivery data | S116: 45866
B117: ZNZ Building 2 | C117: 2025 | D117: Jan 2025 | E117: Feb 2025 | F117: 2 | G117: Nomuhub ad account | H117: Inactive | I117: Messages | J117: 2085.28 | K117: SAR | L117: =IF(K117="USD",J117*$Q$7,J117) -> 2085.28 | M117: 124 | N117: =IFERROR(L117/M117,"") -> 16.816774 | O117: 63627 | P117: 37232 | R117: Meta delivery data | S117: 45676
B118: Sala MSG | C118: 2025 | D118: Jul 2025 | E118: Aug 2025 | F118: 2 | G118: Nomuhub ad account | H118: Inactive | I118: Messages | J118: 1957.92 | K118: SAR | L118: =IF(K118="USD",J118*$Q$7,J118) -> 1957.92 | M118: 169 | N118: =IFERROR(L118/M118,"") -> 11.585325 | O118: 28265 | P118: 14405 | Q118: 2 | R118: Meta delivery data | S118: 45861
B119: ZNZ Build | C119: 2025 | D119: Jun 2025 | E119: Jul 2025 | F119: 2 | G119: Nomuhub ad account | H119: Inactive | I119: Messages | J119: 1625.8 | K119: SAR | L119: =IF(K119="USD",J119*$Q$7,J119) -> 1625.8 | M119: 79 | N119: =IFERROR(L119/M119,"") -> 20.579747 | O119: 58386 | P119: 37033 | Q119: 2 | R119: Meta delivery data | S119: 45829
B120: vitnam explore | C120: 2025 | D120: Jul 2025 | E120: Jul 2025 | F120: 1 | G120: Nomuhub ad account | H120: Inactive | I120: Messages | J120: 1585.72 | K120: SAR | L120: =IF(K120="USD",J120*$Q$7,J120) -> 1585.72 | M120: 47 | N120: =IFERROR(L120/M120,"") -> 33.738723 | O120: 48147 | P120: 23043 | R120: Meta delivery data | S120: 45845
B121: Bali teaching | C121: 2025 | D121: Dec 2025 | E121: Dec 2025 | F121: 1 | G121: Nomuhub ad account | H121: Inactive | I121: Messages | J121: 1023.68 | K121: SAR | L121: =IF(K121="USD",J121*$Q$7,J121) -> 1023.68 | M121: 32 | N121: =IFERROR(L121/M121,"") -> 31.99 | O121: 32286 | P121: 18868 | Q121: 1 | R121: Meta delivery data | S121: 45999
B122: ZnZ teaching | C122: 2025 | D122: Dec 2025 | E122: Dec 2025 | F122: 1 | G122: Nomuhub ad account | H122: Inactive | I122: Messages | J122: 867.25 | K122: SAR | L122: =IF(K122="USD",J122*$Q$7,J122) -> 867.25 | M122: 36 | N122: =IFERROR(L122/M122,"") -> 24.090278 | O122: 32947 | P122: 19499 | R122: Meta delivery data | S122: 46002
B123: BA Teaching | C123: 2025 | D123: May 2025 | E123: May 2025 | F123: 1 | G123: Nomuhub ad account | H123: Inactive | I123: Messages | J123: 856.55 | K123: SAR | L123: =IF(K123="USD",J123*$Q$7,J123) -> 856.55 | M123: 117 | N123: =IFERROR(L123/M123,"") -> 7.3209402 | O123: 31331 | P123: 17667 | Q123: 1 | R123: Meta delivery data | S123: 45792
B124: Znz Building | C124: 2025 | D124: May 2025 | E124: May 2025 | F124: 1 | G124: Nomuhub ad account | H124: Inactive | I124: Messages | J124: 843.37 | K124: SAR | L124: =IF(K124="USD",J124*$Q$7,J124) -> 843.37 | M124: 102 | N124: =IFERROR(L124/M124,"") -> 8.2683333 | O124: 18912 | P124: 9849 | Q124: 2 | R124: Meta delivery data | S124: 45783
B125: Thailan Wellness MSG - 2026 | C125: 2025 | D125: Dec 2025 | E125: Dec 2025 | F125: 1 | G125: Nomuhub ad account | H125: Inactive | I125: Messages | J125: 508.4 | K125: SAR | L125: =IF(K125="USD",J125*$Q$7,J125) -> 508.4 | M125: 28 | N125: =IFERROR(L125/M125,"") -> 18.157143 | O125: 11225 | P125: 6982 | R125: Meta delivery data | S125: 46019
B126: ZNZ Build MSG - 2026 | C126: 2025 | D126: Dec 2025 | E126: Dec 2025 | F126: 1 | G126: Nomuhub ad account | H126: Inactive | I126: Messages | J126: 420.58 | K126: SAR | L126: =IF(K126="USD",J126*$Q$7,J126) -> 420.58 | M126: 40 | N126: =IFERROR(L126/M126,"") -> 10.5145 | O126: 35199 | P126: 20296 | R126: Meta delivery data | S126: 46019
B127: Sales Bali well Dec | C127: 2025 | D127: Nov 2025 | E127: Nov 2025 | F127: 1 | G127: Nomuhub ad account | H127: Inactive | I127: No delivery | J127: 250.37 | K127: SAR | L127: =IF(K127="USD",J127*$Q$7,J127) -> 250.37 | N127: =IFERROR(L127/M127,"") | O127: 5270 | P127: 2877 | R127: Meta delivery data | S127: 45971
...
